[
  {
    "id": "1",
    "total_orders": 44,
    "icy_orders": 20
  },
  {
    "id": "2",
    "total_orders": 115,
    "icy_orders": 56
  },
  {
    "id": "3",
    "total_orders": 133,
    "icy_orders": null
  },
  {
    "id": "4",
    "total_orders": 139,
    "icy_orders": null
  },
  {
    "id": "5",
    "total_orders": 191,
    "icy_orders": 89
  },
  {
    "id": "6",
    "total_orders": 85,
    "icy_orders": 50
  },
  {
    "id": "7",
    "total_orders": 186,
    "icy_orders": null
  },
  {
    "id": "8",
    "total_orders": 86,
    "icy_orders": null
  },
  {
    "id": "9",
    "total_orders": 80,
    "icy_orders": 54
  },
  {
    "id": "10",
    "total_orders": 51,
    "icy_orders": 30
  },
  {
    "id": "11",
    "total_orders": 203,
    "icy_orders": 144
  },
  {
    "id": "12",
    "total_orders": 41,
    "icy_orders": 2
  },
  {
    "id": "13",
    "total_orders": 187,
    "icy_orders": null
  },
  {
    "id": "14",
    "total_orders": 88,
    "icy_orders": 39
  },
  {
    "id": "15",
    "total_orders": 112,
    "icy_orders": 53
  },
  {
    "id": "16",
    "total_orders": 210,
    "icy_orders": null
  },
  {
    "id": "17",
    "total_orders": 69,
    "icy_orders": 37
  },
  {
    "id": "18",
    "total_orders": 101,
    "icy_orders": 86
  },
  {
    "id": "19",
    "total_orders": 256,
    "icy_orders": 25
  },
  {
    "id": "20",
    "total_orders": 125,
    "icy_orders": null
  },
  {
    "id": "21",
    "total_orders": 169,
    "icy_orders": 131
  },
  {
    "id": "22",
    "total_orders": 119,
    "icy_orders": 12
  },
  {
    "id": "23",
    "total_orders": 48,
    "icy_orders": 33
  },
  {
    "id": "24",
    "total_orders": 188,
    "icy_orders": 121
  },
  {
    "id": "25",
    "total_orders": 267,
    "icy_orders": null
  },
  {
    "id": "26",
    "total_orders": 184,
    "icy_orders": null
  },
  {
    "id": "27",
    "total_orders": 257,
    "icy_orders": null
  },
  {
    "id": "28",
    "total_orders": 61,
    "icy_orders": 40
  },
  {
    "id": "29",
    "total_orders": 109,
    "icy_orders": 72
  },
  {
    "id": "30",
    "total_orders": 198,
    "icy_orders": null
  },
  {
    "id": "31",
    "total_orders": 85,
    "icy_orders": null
  },
  {
    "id": "32",
    "total_orders": 228,
    "icy_orders": null
  },
  {
    "id": "33",
    "total_orders": 182,
    "icy_orders": null
  },
  {
    "id": "34",
    "total_orders": 154,
    "icy_orders": 102
  },
  {
    "id": "35",
    "total_orders": 138,
    "icy_orders": 21
  },
  {
    "id": "36",
    "total_orders": 27,
    "icy_orders": 14
  },
  {
    "id": "37",
    "total_orders": 121,
    "icy_orders": 46
  },
  {
    "id": "38",
    "total_orders": 18,
    "icy_orders": 11
  },
  {
    "id": "39",
    "total_orders": 89,
    "icy_orders": 53
  },
  {
    "id": "40",
    "total_orders": 111,
    "icy_orders": null
  },
  {
    "id": "41",
    "total_orders": 291,
    "icy_orders": null
  },
  {
    "id": "42",
    "total_orders": 139,
    "icy_orders": null
  },
  {
    "id": "43",
    "total_orders": 34,
    "icy_orders": null
  },
  {
    "id": "44",
    "total_orders": 156,
    "icy_orders": null
  },
  {
    "id": "45",
    "total_orders": 31,
    "icy_orders": 21
  },
  {
    "id": "46",
    "total_orders": 278,
    "icy_orders": 72
  },
  {
    "id": "47",
    "total_orders": 211,
    "icy_orders": 146
  },
  {
    "id": "48",
    "total_orders": 224,
    "icy_orders": null
  },
  {
    "id": "49",
    "total_orders": 104,
    "icy_orders": 44
  },
  {
    "id": "50",
    "total_orders": 184,
    "icy_orders": null
  }
]